<?xml version="1.0" encoding="gb2312"?>
<iTStation>
  <TradingTimes>

    <SSE ExchangeName="上证">
      <Day>
        <Section Begin="9:30" End="11:30" />
        <Section Begin="13:00" End="15:00" />
      </Day>
    </SSE>

    <SZE ExchangeName="深证">
      <Day>
        <Section Begin="9:30" End="11:30" />
        <Section Begin="13:00" End="15:00" />
      </Day>
    </SZE>

    <CFFEX ExchangeName="中金所">
      <Day InstrumentID="IF,IC,IH">
        <Section Begin="9:30" End="11:30" />
        <Section Begin="13:00" End="15:00" />
      </Day>
	   <Day InstrumentID="T,TF">
        <Section Begin="9:15" End="11:30" />
        <Section Begin="13:00" End="15:15" />
      </Day>
    </CFFEX>
    
    <DCE ExchangeName="大商所">
      <Day>
        <Section Begin="9:00" End="10:15" />
        <Section Begin="10:30" End="11:30" />
        <Section Begin="13:30" End="15:00" />
      </Day>
      <Nights>
        <Night InstrumentID="j,p,m,y,a,b,jm,i">
          <Section Begin="21:00" End="23:30" />
        </Night>
      </Nights>
    </DCE>

    <CZCE ExchangeName="郑商所">
      <Day>
        <Section Begin="9:00" End="10:15" />
        <Section Begin="10:30" End="11:30" />
        <Section Begin="13:30" End="15:00" />
      </Day>
      <Nights>
        <Night InstrumentID="SR,CF,RM,MA,ME,TA,FG,OI,TC,ZC">
          <Section Begin="21:00" End="23:30" />
        </Night>
      </Nights>
    </CZCE>

    <SHFE ExchangeName="上期所">
      <Day>
        <Section Begin="9:00" End="10:15" />
        <Section Begin="10:30" End="11:30" />
        <Section Begin="13:30" End="15:00" />
      </Day>
      <Nights>
        <Night InstrumentID="al,cu,zn,pb,ni,sn">
          <Section Begin="21:00" End="1:00" />
        </Night>
        <Night InstrumentID="ag,au">
          <Section Begin="21:00" End="2:30" />
        </Night>
        <Night InstrumentID="ru,rb,hc,bu">
          <Section Begin="21:00" End="23:00" />
        </Night>
      </Nights>
    </SHFE>

    <SGE ExchangeName="金交所">
      <Day>
        <Section Begin="9:00" End="11:30" />
        <Section Begin="13:30" End="15:30" />
      </Day>
      <Nights>
        <Night>
          <Section Begin="20:00" End="2:30" />
        </Night>
      </Nights>
    </SGE>
    
  </TradingTimes>
  
  <!--法定节假日,不包括普通的周六日，但包括是节假日的周六日（且相邻的周五、周一都不是节假日）。因为节假日的前一天（跳过周六日）的晚上是没夜盘的-->
  <Holidays>
	  <YearHoliday Year="2010" Days="0101,0215,0216,0217,0218,0219,0405,0503,0614,0615,0616,0922,0923,0924,1001,1004,1005,1006,1007" />
	  <YearHoliday Year="2011" Days="0103,0202,0203,0204,0207,0208,0404,0405,0502,0606,0912,1003,1004,1005,1006,1007" />
	  <YearHoliday Year="2012" Days="0102,0103,0123,0124,0125,0126,0127,0402,0403,0404,0430,0501,0622,1001,1002,1003,1004,1005" />
	  <YearHoliday Year="2013" Days="0101,0102,0103,0211,0212,0213,0214,0215,0404,0405,0429,0430,0501,0610,0611,0612,0919,0920,1001,1002,1003,1004,1007" />
	  <YearHoliday Year="2014" Days="0101,0131,0203,0204,0205,0206,0407,0501,0502,0602,0908,1001,1002,1003,1006,1007" />
	  <YearHoliday Year="2015" Days="0101,0102,0218,0219,0220,0223,0224,0406,0501,0622,0903,0904,0927,1001,1002,1005,1006,1007" />
	  <YearHoliday Year="2016" Days="0101,0207,0208,0209,0210,0211,0212,0213,0404,0502,0609,0610,0611,0915,0916,0917,1003,1004,1005,1006,1007" />
	  <YearHoliday Year="2017" Days="0102,0127,0130,0131,0201,0202,0403,,0404,0501,0529,0530,1002,1003,1004,1005,1006" />
  </Holidays>
</iTStation>